[{"id":401858209,"season":2026,"week":1,"seasonType":"regular","startDate":"2026-09-05T04:00:00.000Z","startTimeTBD":true,"completed":false,"neutralSite":false,"conferenceGame":false,"attendance":null,"venueId":3982,"venue":"Wallace Wade Stadium","homeId":150,"homeTeam":"Duke","homeClassification":"fbs","homeConference":"ACC","homePoints":null,"homeLineScores":null,"homePostgameWinProbability":null,"homePregameElo":null,"homePostgameElo":null,"awayId":2655,"awayTeam":"Tulane","awayClassification":"fbs","awayConference":"American Athletic","awayPoints":null,"awayLineScores":null,"awayPostgameWinProbability":null,"awayPregameElo":null,"awayPostgameElo":null,"excitementIndex":null,"highlights":"","notes":null},{"id":401858217,"season":2026,"week":2,"seasonType":"regular","startDate":"2026-09-12T04:00:00.000Z","startTimeTBD":true,"completed":false,"neutralSite":false,"conferenceGame":false,"attendance":null,"venueId":3832,"venue":"Memorial Stadium (Champaign, IL)","homeId":356,"homeTeam":"Illinois","homeClassification":"fbs","homeConference":"Big Ten","homePoints":null,"homeLineScores":null,"homePostgameWinProbability":null,"homePregameElo":null,"homePostgameElo":null,"awayId":150,"awayTeam":"Duke","awayClassification":"fbs","awayConference":"ACC","awayPoints":null,"awayLineScores":null,"awayPostgameWinProbability":null,"awayPregameElo":null,"awayPostgameElo":null,"excitementIndex":null,"highlights":"","notes":null},{"id":401858231,"season":2026,"week":3,"seasonType":"regular","startDate":"2026-09-19T04:00:00.000Z","startTimeTBD":true,"completed":false,"neutralSite":false,"conferenceGame":true,"attendance":null,"venueId":3982,"venue":"Wallace Wade Stadium","homeId":150,"homeTeam":"Duke","homeClassification":"fbs","homeConference":"ACC","homePoints":null,"homeLineScores":null,"homePostgameWinProbability":null,"homePregameElo":null,"homePostgameElo":null,"awayId":24,"awayTeam":"Stanford","awayClassification":"fbs","awayConference":"ACC","awayPoints":null,"awayLineScores":null,"awayPostgameWinProbability":null,"awayPregameElo":null,"awayPostgameElo":null,"excitementIndex":null,"highlights":"","notes":null},{"id":401858244,"season":2026,"week":4,"seasonType":"regular","startDate":"2026-09-26T04:00:00.000Z","startTimeTBD":true,"completed":false,"neutralSite":false,"conferenceGame":false,"attendance":null,"venueId":3982,"venue":"Wallace Wade Stadium","homeId":150,"homeTeam":"Duke","homeClassification":"fbs","homeConference":"ACC","homePoints":null,"homeLineScores":null,"homePostgameWinProbability":null,"homePregameElo":null,"homePostgameElo":null,"awayId":2729,"awayTeam":"William & Mary","awayClassification":"fcs","awayConference":"CAA","awayPoints":null,"awayLineScores":null,"awayPostgameWinProbability":null,"awayPregameElo":null,"awayPostgameElo":null,"excitementIndex":null,"highlights":"","notes":null},{"id":401858255,"season":2026,"week":6,"seasonType":"regular","startDate":"2026-10-10T04:00:00.000Z","startTimeTBD":true,"completed":false,"neutralSite":false,"conferenceGame":true,"attendance":null,"venueId":721,"venue":"Bobby Dodd Stadium","homeId":59,"homeTeam":"Georgia Tech","homeClassification":"fbs","homeConference":"ACC","homePoints":null,"homeLineScores":null,"homePostgameWinProbability":null,"homePregameElo":null,"homePostgameElo":null,"awayId":150,"awayTeam":"Duke","awayClassification":"fbs","awayConference":"ACC","awayPoints":null,"awayLineScores":null,"awayPostgameWinProbability":null,"awayPregameElo":null,"awayPostgameElo":null,"excitementIndex":null,"highlights":"","notes":null},{"id":401858266,"season":2026,"week":7,"seasonType":"regular","startDate":"2026-10-17T04:00:00.000Z","startTimeTBD":true,"completed":false,"neutralSite":false,"conferenceGame":true,"attendance":null,"venueId":3982,"venue":"Wallace Wade Stadium","homeId":150,"homeTeam":"Duke","homeClassification":"fbs","homeConference":"ACC","homePoints":null,"homeLineScores":null,"homePostgameWinProbability":null,"homePregameElo":null,"homePostgameElo":null,"awayId":153,"awayTeam":"North Carolina","awayClassification":"fbs","awayConference":"ACC","awayPoints":null,"awayLineScores":null,"awayPostgameWinProbability":null,"awayPregameElo":null,"awayPostgameElo":null,"excitementIndex":null,"highlights":"","notes":null},{"id":401858271,"season":2026,"week":8,"seasonType":"regular","startDate":"2026-10-23T04:00:00.000Z","startTimeTBD":true,"completed":false,"neutralSite":false,"conferenceGame":true,"attendance":null,"venueId":3923,"venue":"Scott Stadium","homeId":258,"homeTeam":"Virginia","homeClassification":"fbs","homeConference":"ACC","homePoints":null,"homeLineScores":null,"homePostgameWinProbability":null,"homePregameElo":null,"homePostgameElo":null,"awayId":150,"awayTeam":"Duke","awayClassification":"fbs","awayConference":"ACC","awayPoints":null,"awayLineScores":null,"awayPostgameWinProbability":null,"awayPregameElo":null,"awayPostgameElo":null,"excitementIndex":null,"highlights":"","notes":"Will be played Oct. 23 or Oct. 24"},{"id":401858279,"season":2026,"week":9,"seasonType":"regular","startDate":"2026-10-31T04:00:00.000Z","startTimeTBD":true,"completed":false,"neutralSite":false,"conferenceGame":true,"attendance":null,"venueId":3982,"venue":"Wallace Wade Stadium","homeId":150,"homeTeam":"Duke","homeClassification":"fbs","homeConference":"ACC","homePoints":null,"homeLineScores":null,"homePostgameWinProbability":null,"homePregameElo":null,"homePostgameElo":null,"awayId":103,"awayTeam":"Boston College","awayClassification":"fbs","awayConference":"ACC","awayPoints":null,"awayLineScores":null,"awayPostgameWinProbability":null,"awayPregameElo":null,"awayPostgameElo":null,"excitementIndex":null,"highlights":"","notes":null},{"id":401858286,"season":2026,"week":10,"seasonType":"regular","startDate":"2026-11-06T05:00:00.000Z","startTimeTBD":true,"completed":false,"neutralSite":false,"conferenceGame":true,"attendance":null,"venueId":3670,"venue":"Carter-Finley Stadium","homeId":152,"homeTeam":"NC State","homeClassification":"fbs","homeConference":"ACC","homePoints":null,"homeLineScores":null,"homePostgameWinProbability":null,"homePregameElo":null,"homePostgameElo":null,"awayId":150,"awayTeam":"Duke","awayClassification":"fbs","awayConference":"ACC","awayPoints":null,"awayLineScores":null,"awayPostgameWinProbability":null,"awayPregameElo":null,"awayPostgameElo":null,"excitementIndex":null,"highlights":"","notes":"Will be played Nov. 6 or Nov. 7"},{"id":401858296,"season":2026,"week":11,"seasonType":"regular","startDate":"2026-11-14T05:00:00.000Z","startTimeTBD":true,"completed":false,"neutralSite":false,"conferenceGame":true,"attendance":null,"venueId":3948,"venue":"Hard Rock Stadium","homeId":2390,"homeTeam":"Miami","homeClassification":"fbs","homeConference":"ACC","homePoints":null,"homeLineScores":null,"homePostgameWinProbability":null,"homePregameElo":null,"homePostgameElo":null,"awayId":150,"awayTeam":"Duke","awayClassification":"fbs","awayConference":"ACC","awayPoints":null,"awayLineScores":null,"awayPostgameWinProbability":null,"awayPregameElo":null,"awayPostgameElo":null,"excitementIndex":null,"highlights":"","notes":null},{"id":401858303,"season":2026,"week":12,"seasonType":"regular","startDate":"2026-11-21T05:00:00.000Z","startTimeTBD":true,"completed":false,"neutralSite":false,"conferenceGame":true,"attendance":null,"venueId":3982,"venue":"Wallace Wade Stadium","homeId":150,"homeTeam":"Duke","homeClassification":"fbs","homeConference":"ACC","homePoints":null,"homeLineScores":null,"homePostgameWinProbability":null,"homePregameElo":null,"homePostgameElo":null,"awayId":228,"awayTeam":"Clemson","awayClassification":"fbs","awayConference":"ACC","awayPoints":null,"awayLineScores":null,"awayPostgameWinProbability":null,"awayPregameElo":null,"awayPostgameElo":null,"excitementIndex":null,"highlights":"","notes":null},{"id":401858312,"season":2026,"week":13,"seasonType":"regular","startDate":"2026-11-28T05:00:00.000Z","startTimeTBD":true,"completed":false,"neutralSite":false,"conferenceGame":true,"attendance":null,"venueId":3630,"venue":"Allegacy Federal Credit Union Stadium","homeId":154,"homeTeam":"Wake Forest","homeClassification":"fbs","homeConference":"ACC","homePoints":null,"homeLineScores":null,"homePostgameWinProbability":null,"homePregameElo":null,"homePostgameElo":null,"awayId":150,"awayTeam":"Duke","awayClassification":"fbs","awayConference":"ACC","awayPoints":null,"awayLineScores":null,"awayPostgameWinProbability":null,"awayPregameElo":null,"awayPostgameElo":null,"excitementIndex":null,"highlights":"","notes":null}]