[{"id":250010275,"season":2004,"week":1,"seasonType":"postseason","startDate":"2005-01-01T16:00:00.000Z","startTimeTBD":false,"completed":true,"neutralSite":true,"conferenceGame":false,"attendance":0,"venueId":347,"venue":"Camp Randall Stadium","homeId":275,"homeTeam":"Wisconsin","homeClassification":"fbs","homeConference":"Big Ten","homePoints":21,"homeLineScores":[3,3,7,8],"homePostgameWinProbability":null,"homePregameElo":1638,"homePostgameElo":1649,"awayId":61,"awayTeam":"Georgia","awayClassification":"fbs","awayConference":"SEC","awayPoints":24,"awayLineScores":[3,7,14,0],"awayPostgameWinProbability":null,"awayPregameElo":1916,"awayPostgameElo":1905,"excitementIndex":null,"highlights":"","notes":"OUTBACK BOWL"}]